CHANGES.txt
DEPENDENCES.txt
README.txt
setup.py
src/ng/__init__.py
src/ng.site.addon.comment.egg-info/PKG-INFO
src/ng.site.addon.comment.egg-info/SOURCES.txt
src/ng.site.addon.comment.egg-info/dependency_links.txt
src/ng.site.addon.comment.egg-info/namespace_packages.txt
src/ng.site.addon.comment.egg-info/not-zip-safe
src/ng.site.addon.comment.egg-info/requires.txt
src/ng.site.addon.comment.egg-info/top_level.txt
src/ng/site/__init__.py
src/ng/site/addon/__init__.py
src/ng/site/addon/comment/__init__.py
src/ng/site/addon/comment/configure.zcml
src/ng/site/addon/comment/ng.site.addon.comment.txt
src/ng/site/addon/comment/comment/__init__.py
src/ng/site/addon/comment/comment/configure.zcml
src/ng/site/addon/comment/convert/__init__.py
src/ng/site/addon/comment/convert/configure.zcml
src/ng/site/addon/comment/etc/ng.site.addon.comment-configure.zcml
src/ng/site/addon/comment/install/__init__.py
src/ng/site/addon/comment/install/configure.zcml
src/ng/site/addon/comment/install/install_converter.py
src/ng/site/addon/comment/profile/__init__.py
src/ng/site/addon/comment/profile/configure.zcml
src/ng/site/addon/comment/profile/create_profile_handle.py